<?xml version="1.0" encoding="UTF-8"?>
<!DOCTYPE buildprofiles SYSTEM "https://resources.jetbrains.com/writerside/1.0/build-profiles.dtd">
<buildprofiles xsi:noNamespaceSchemaLocation="https://resources.jetbrains.com/writerside/1.0/build-profiles.xsd"
               xmlns:xsi="http://www.w3.org/2001/XMLSchema-instance">

    <build-profile instance="l">
        <variables>
            <noindex-content>true</noindex-content>
            <primary-color>dracula</primary-color>
            <color-preset>soft</color-preset>
            <!-- Header section  -->
            <download-title>Github</download-title>
            <download-page>https://github.com/IsMikeTaken/ProtobuffEncoder</download-page>
            <showDownloadButton>true</showDownloadButton>
            <!-- Header end -->
        </variables>
    </build-profile>

</buildprofiles>
